tinypg/__init__.py
tinypg/binaries.py
tinypg/config.py
tinypg/context.py
tinypg/core.py
tinypg/exceptions.py
tinypg/extensions.py
tinypg/port_manager.py
tinypg/docs/__init__.py
tinypg/docs/extensions.py
tinypg-0.3.0.dist-info/METADATA
tinypg-0.3.0.dist-info/WHEEL
tinypg-0.3.0.dist-info/top_level.txt
tinypg-0.3.0.dist-info/RECORD
