Metadata-Version: 2.4
Name: tinypg
Version: 0.3.0
Summary: Ephemeral PostgreSQL databases for Python development and testing
Author-email: kketch <9odxnqhjr@mozmail.com>
License: MIT
Project-URL: Homepage, https://github.com/kketch/tinypg
Project-URL: Documentation, https://python-tinypg.readthedocs.io
Project-URL: Repository, https://github.com/kketch/tinypg
Classifier: Intended Audience :: Developers
Classifier: License :: OSI Approved :: MIT License
Classifier: Operating System :: POSIX :: Linux
Classifier: Operating System :: MacOS :: MacOS X
Classifier: Programming Language :: Python :: 3
Classifier: Programming Language :: Python :: 3.8
Classifier: Programming Language :: Python :: 3.9
Classifier: Programming Language :: Python :: 3.10
Classifier: Programming Language :: Python :: 3.11
Classifier: Programming Language :: Python :: 3.12
Classifier: Topic :: Database
Classifier: Topic :: Software Development :: Testing
Requires-Python: >=3.8
Requires-Dist: psycopg2-binary>=2.9.0
Requires-Dist: requests>=2.25.0
Provides-Extra: dev
Requires-Dist: pytest>=7.0.0; extra == "dev"
Requires-Dist: pytest-asyncio>=0.21.0; extra == "dev"
Requires-Dist: black>=22.0.0; extra == "dev"
Requires-Dist: isort>=5.10.0; extra == "dev"
Requires-Dist: mypy>=1.0.0; extra == "dev"
Provides-Extra: async
Requires-Dist: asyncpg>=0.29.0; extra == "async"
Provides-Extra: docs
Requires-Dist: pdoc>=14.4; extra == "docs"
